mmar_mapi/__init__.py
mmar_mapi/api.py
mmar_mapi/decorators_maybe_lru_cache.py
mmar_mapi/file_storage.py
mmar_mapi/models/__init__.py
mmar_mapi/models/base.py
mmar_mapi/models/chat.py
mmar_mapi/models/enums.py
mmar_mapi/models/tracks.py
mmar_mapi/models/widget.py
mmar_mapi/py.typed
mmar_mapi/s.py
mmar_mapi/services/__init__.py
mmar_mapi/services/document_extractor.py
mmar_mapi/services/llm_hub.py
mmar_mapi/tracks.py
mmar_mapi/type_union.py
mmar_mapi/utils.py
mmar_mapi/utils_import.py
mmar_mapi/xml_parser.py
mmar_mapi-1.4.4.dist-info/licenses/LICENSE
mmar_mapi-1.4.4.dist-info/WHEEL
mmar_mapi-1.4.4.dist-info/METADATA
mmar_mapi-1.4.4.dist-info/RECORD
